modelengine_agents/agent_cn/__init__.py
modelengine_agents/agent_cn/_function_type_hints_utils.py
modelengine_agents/agent_cn/agent_types.py
modelengine_agents/agent_cn/agents.py
modelengine_agents/agent_cn/cli.py
modelengine_agents/agent_cn/default_tools.py
modelengine_agents/agent_cn/gradio_ui.py
modelengine_agents/agent_cn/local_python_executor.py
modelengine_agents/agent_cn/memory.py
modelengine_agents/agent_cn/models.py
modelengine_agents/agent_cn/monitoring.py
modelengine_agents/agent_cn/remote_executors.py
modelengine_agents/agent_cn/tool_validation.py
modelengine_agents/agent_cn/tools.py
modelengine_agents/agent_cn/utils.py
modelengine_agents/agent_cn/vision_web_browser.py
modelengine_agents/agent_cn/prompts/code_agent.yaml
modelengine_agents/agent_cn/prompts/toolcalling_agent.yaml
modelengine_agents/agent_en/__init__.py
modelengine_agents/agent_en/_function_type_hints_utils.py
modelengine_agents/agent_en/agent_types.py
modelengine_agents/agent_en/agents.py
modelengine_agents/agent_en/cli.py
modelengine_agents/agent_en/default_tools.py
modelengine_agents/agent_en/gradio_ui.py
modelengine_agents/agent_en/local_python_executor.py
modelengine_agents/agent_en/memory.py
modelengine_agents/agent_en/models.py
modelengine_agents/agent_en/monitoring.py
modelengine_agents/agent_en/remote_executors.py
modelengine_agents/agent_en/tool_validation.py
modelengine_agents/agent_en/tools.py
modelengine_agents/agent_en/utils.py
modelengine_agents/agent_en/vision_web_browser.py
modelengine_agents/agent_en/prompts/code_agent.yaml
modelengine_agents/agent_en/prompts/toolcalling_agent.yaml
modelengine_agents/core/__init__.py
modelengine_agents/core/config.py
modelengine_agents/core/server.py
modelengine_agents/core/agents/CodeAgentME.py
modelengine_agents/core/agents/ToolCallingAgentME.py
modelengine_agents/core/apps/test_app.py
modelengine_agents/core/models/LiteLLMModelME.py
modelengine_agents/core/models/OpenAIServerModelME.py
modelengine_agents/core/models/test_model.py
modelengine_agents-0.1.4.dist-info/METADATA
modelengine_agents-0.1.4.dist-info/WHEEL
modelengine_agents-0.1.4.dist-info/top_level.txt
modelengine_agents-0.1.4.dist-info/RECORD
